test_sys_executable_vs_capi/__init__.py
test_sys_executable_vs_capi/test_sys_executable.cpython-39-x86_64-linux-gnu.so
test_sys_executable_vs_capi-0.1.2.dist-info/METADATA
test_sys_executable_vs_capi-0.1.2.dist-info/WHEEL
test_sys_executable_vs_capi-0.1.2.dist-info/RECORD
test_sys_executable_vs_capi-0.1.2.dist-info/top_level.txt
