Metadata-Version: 2.1
Name: test-sys-executable-vs-capi
Version: 0.1.2
Summary: Verify that sys.executable and Py_GetProgramFullPath are in agreement
Home-page: https://github.com/TyberiusPrime/test_sys_executable_vs_capi
Author: Florian Finkernagel
Author-email: finkernagel@imt.uni-marburg.de
